LICENSE
MANIFEST.in
README.md
setup.py
aiearth/deeplearning/__init__.py
aiearth/deeplearning/cloud/__init__.py
aiearth/deeplearning/cloud/aie_client.py
aiearth/deeplearning/cloud/model.py
aiearth/deeplearning/cloud/trainer.py
aiearth/deeplearning/cloud/datasets/__init__.py
aiearth/deeplearning/cloud/datasets/aie_dataset.py
aiearth/deeplearning/cloud/datasets/aie_dataset_get_url.py
aiearth/deeplearning/cloud/datasets/public_dataset_meta.py
aiearth/deeplearning/datasets/__init__.py
aiearth/deeplearning/datasets/datasets.py
aiearth/deeplearning/datasets/common/__init__.py
aiearth/deeplearning/datasets/common/cv_ann_writer.py
aiearth/deeplearning/datasets/common/geo_transfer.py
aiearth/deeplearning/datasets/mmseg/__init__.py
aiearth/deeplearning/datasets/mmseg/changedet/__init__.py
aiearth/deeplearning/datasets/mmseg/changedet/buildingchange.py
aiearth/deeplearning/datasets/mmseg/changedet/changedet.py
aiearth/deeplearning/datasets/mmseg/changedet/coco_evaluator.py
aiearth/deeplearning/datasets/mmseg/changedet/pipelines/__init__.py
aiearth/deeplearning/datasets/mmseg/changedet/pipelines/double_img_formating.py
aiearth/deeplearning/datasets/mmseg/changedet/pipelines/double_img_loading.py
aiearth/deeplearning/datasets/mmseg/changedet/pipelines/double_img_transforms.py
aiearth/deeplearning/datasets/mmseg/changedet/pipelines/test_time_aug.py
aiearth/deeplearning/datasets/mmseg/landcover/__init__.py
aiearth/deeplearning/datasets/mmseg/landcover/landcover.py
aiearth/deeplearning/datasets/mmseg/target_extraction/__init__.py
aiearth/deeplearning/datasets/mmseg/target_extraction/remote_sensing.py
aiearth/deeplearning/datasets/mmseg/target_extraction/pipelines/__init__.py
aiearth/deeplearning/datasets/mmseg/target_extraction/pipelines/autoaugment.py
aiearth/deeplearning/datasets/mmseg/target_extraction/pipelines/custom_transforms.py
aiearth/deeplearning/datasets/mmseg/target_extraction/pipelines/randaug.py
aiearth_deeplearning.egg-info/PKG-INFO
aiearth_deeplearning.egg-info/SOURCES.txt
aiearth_deeplearning.egg-info/dependency_links.txt
aiearth_deeplearning.egg-info/requires.txt
aiearth_deeplearning.egg-info/top_level.txt