Metadata-Version: 2.1
Name: aiearth-deeplearning
Version: 0.0.2
Summary: AI Earth algo sdk builded by torch && mmseg
Author: AI Earth developer team
Author-email: yuanbin.myb@alibaba-inc.com
Requires-Python: >=3.7.2
License-File: LICENSE
